ritify-1.0.2.dist-info/METADATA
ritify-1.0.2.dist-info/WHEEL
ritify-1.0.2.dist-info/entry_points.txt
ritify/.DS_Store
ritify/LICENSE
ritify/__init__.py
ritify/rich/__init__.py
ritify/rich/__main__.py
ritify/rich/_cell_widths.py
ritify/rich/_emoji_codes.py
ritify/rich/_emoji_replace.py
ritify/rich/_export_format.py
ritify/rich/_extension.py
ritify/rich/_fileno.py
ritify/rich/_inspect.py
ritify/rich/_log_render.py
ritify/rich/_loop.py
ritify/rich/_null_file.py
ritify/rich/_palettes.py
ritify/rich/_pick.py
ritify/rich/_ratio.py
ritify/rich/_spinners.py
ritify/rich/_stack.py
ritify/rich/_timer.py
ritify/rich/_win32_console.py
ritify/rich/_windows.py
ritify/rich/_windows_renderer.py
ritify/rich/_wrap.py
ritify/rich/abc.py
ritify/rich/align.py
ritify/rich/ansi.py
ritify/rich/bar.py
ritify/rich/box.py
ritify/rich/cells.py
ritify/rich/color.py
ritify/rich/color_triplet.py
ritify/rich/columns.py
ritify/rich/console.py
ritify/rich/constrain.py
ritify/rich/containers.py
ritify/rich/control.py
ritify/rich/default_styles.py
ritify/rich/diagnose.py
ritify/rich/emoji.py
ritify/rich/errors.py
ritify/rich/file_proxy.py
ritify/rich/filesize.py
ritify/rich/highlighter.py
ritify/rich/json.py
ritify/rich/jupyter.py
ritify/rich/layout.py
ritify/rich/live.py
ritify/rich/live_render.py
ritify/rich/logging.py
ritify/rich/markdown.py
ritify/rich/markup.py
ritify/rich/measure.py
ritify/rich/padding.py
ritify/rich/pager.py
ritify/rich/palette.py
ritify/rich/panel.py
ritify/rich/pretty.py
ritify/rich/progress.py
ritify/rich/progress_bar.py
ritify/rich/prompt.py
ritify/rich/protocol.py
ritify/rich/region.py
ritify/rich/repr.py
ritify/rich/rule.py
ritify/rich/scope.py
ritify/rich/screen.py
ritify/rich/segment.py
ritify/rich/spinner.py
ritify/rich/status.py
ritify/rich/style.py
ritify/rich/styled.py
ritify/rich/syntax.py
ritify/rich/table.py
ritify/rich/terminal_theme.py
ritify/rich/text.py
ritify/rich/theme.py
ritify/rich/themes.py
ritify/rich/traceback.py
ritify/rich/tree.py
ritify-1.0.2.dist-info/RECORD
