Metadata-Version: 2.1
Name: ritify
Version: 1.0.2
Summary: A rich console for Python
Author-Email: Alex Graham <destgraham@icloud.com>
License: MIT
Requires-Python: >=3.13
Requires-Dist: pygments>=2.18.0
Requires-Dist: markdown-it-py>=3.0.0
Requires-Dist: wcwidth>=0.2.13
Requires-Dist: emoji>=2.14.0
